gsMap/__init__.py
gsMap/__main__.py
gsMap/cauchy_combination_test.py
gsMap/config.py
gsMap/create_slice_mean.py
gsMap/diagnosis.py
gsMap/find_latent_representation.py
gsMap/format_sumstats.py
gsMap/generate_ldscore.py
gsMap/latent_to_gene.py
gsMap/main.py
gsMap/report.py
gsMap/run_all_mode.py
gsMap/setup.py
gsMap/spatial_ldsc_multiple_sumstats.py
gsMap/visualize.py
gsMap/GNN/__init__.py
gsMap/GNN/adjacency_matrix.py
gsMap/GNN/model.py
gsMap/GNN/train.py
gsMap/templates/report_template.html
gsMap/utils/__init__.py
gsMap/utils/generate_r2_matrix.py
gsMap/utils/jackknife.py
gsMap/utils/manhattan_plot.py
gsMap/utils/regression_read.py
gsMap/utils/torch_utils.py
gsmap-1.73.6.dist-info/entry_points.txt
gsmap-1.73.6.dist-info/licenses/LICENSE
gsmap-1.73.6.dist-info/WHEEL
gsmap-1.73.6.dist-info/METADATA
gsmap-1.73.6.dist-info/RECORD
