Metadata-Version: 2.4
Name: gsMap
Version: 1.73.6
Summary: Genetically informed spatial mapping of cells for complex traits
Author-email: liyang <songliyang@westlake.edu.cn>, wenhao <chenwenhao@westlake.edu.cn>
Requires-Python: >=3.10
Classifier: Development Status :: 3 - Alpha
Classifier: Intended Audience :: Developers
Classifier: License :: OSI Approved :: MIT License
Classifier: Programming Language :: Python :: 3.10
Classifier: Programming Language :: Python :: 3.11
Classifier: Programming Language :: Python :: 3.12
Classifier: Operating System :: POSIX :: Linux
License-File: LICENSE
Requires-Dist: numpy < 2.0.0
Requires-Dist: pandas
Requires-Dist: scipy
Requires-Dist: scikit-learn
Requires-Dist: matplotlib
Requires-Dist: seaborn
Requires-Dist: tqdm
Requires-Dist: pyyaml
Requires-Dist: torch
Requires-Dist: torch-geometric
Requires-Dist: pyranges
Requires-Dist: pyfiglet
Requires-Dist: plotly
Requires-Dist: kaleido
Requires-Dist: jinja2
Requires-Dist: scanpy >=1.8.0
Requires-Dist: zarr>=2,<3
Requires-Dist: bitarray >=2.9.2, <3.0.0
Requires-Dist: pyarrow
Requires-Dist: scikit-misc
Requires-Dist: numba
Requires-Dist: sphinx ; extra == "doc"
Requires-Dist: sphinx-argparse ; extra == "doc"
Requires-Dist: sphinx-autobuild ; extra == "doc"
Requires-Dist: sphinx-autodoc-typehints ; extra == "doc"
Requires-Dist: sphinx-basic-ng ; extra == "doc"
Requires-Dist: sphinx-charts ; extra == "doc"
Requires-Dist: sphinx-copybutton ; extra == "doc"
Requires-Dist: sphinx_inline_tabs ; extra == "doc"
Requires-Dist: sphinx-markdown-tables ; extra == "doc"
Requires-Dist: sphinx-rtd-theme ; extra == "doc"
Requires-Dist: sphinxcontrib-applehelp ; extra == "doc"
Requires-Dist: sphinxcontrib-devhelp ; extra == "doc"
Requires-Dist: sphinxcontrib-htmlhelp ; extra == "doc"
Requires-Dist: sphinxcontrib-jquery ; extra == "doc"
Requires-Dist: sphinxcontrib-jsmath ; extra == "doc"
Requires-Dist: sphinxcontrib-qthelp ; extra == "doc"
Requires-Dist: sphinxcontrib-serializinghtml ; extra == "doc"
Requires-Dist: furo ; extra == "doc"
Requires-Dist: myst-parser ; extra == "doc"
Requires-Dist: nbsphinx ; extra == "doc"
Requires-Dist: pytest>=7.0.0 ; extra == "tests"
Requires-Dist: pytest-cov>=4.0.0 ; extra == "tests"
Requires-Dist: coverage ; extra == "tests"
Project-URL: Documentation, https://yanglab.westlake.edu.cn/gsmap/document/software
Project-URL: Home, https://github.com/JianYang-Lab/gsMap
Project-URL: Website, https://yanglab.westlake.edu.cn/gsmap/home
Provides-Extra: doc
Provides-Extra: tests
